tests
zilean
