Metadata-Version: 2.1
Name: zilean
Version: 0.0.2
Summary: A package that manipulates data for forest fire classification.
Author: Zhihao (Johnson) Du
Author-email: johnsondzh@gmail.com
License: MIT License
Keywords: league-of-legends,machine-learning,data-analysis
Classifier: Programming Language :: Python :: 3
Classifier: License :: OSI Approved :: MIT License
Classifier: Operating System :: OS Independent
License-File: LICENSE
